Metadata-Version: 2.4
Name: django-cookie-consent
Version: 0.9.0
Summary: Django cookie consent application
Author-email: Informatika Mihelac <bmihelac@mihelac.org>
License-Expression: BSD-2-Clause-first-lines
Project-URL: Documentation, https://django-cookie-consent.readthedocs.io/en/latest/
Project-URL: Changelog, https://github.com/django-commons/django-cookie-consent/blob/master/docs/changelog.rst
Project-URL: Bug Tracker, https://github.com/django-commons/django-cookie-consent/issues
Project-URL: Source Code, https://github.com/django-commons/django-cookie-consent
Keywords: cookies,cookie-consent,cookie bar
Classifier: Development Status :: 4 - Beta
Classifier: Framework :: Django
Classifier: Framework :: Django :: 4.2
Classifier: Framework :: Django :: 5.1
Classifier: Framework :: Django :: 5.2
Classifier: Intended Audience :: Developers
Classifier: Operating System :: Unix
Classifier: Operating System :: MacOS
Classifier: Operating System :: Microsoft :: Windows
Classifier: Operating System :: OS Independent
Classifier: Programming Language :: Python :: 3.10
Classifier: Programming Language :: Python :: 3.11
Classifier: Programming Language :: Python :: 3.12
Classifier: Programming Language :: Python :: 3.13
Classifier: Topic :: Software Development :: Libraries :: Python Modules
Requires-Python: >=3.10
License-File: LICENSE
Requires-Dist: django>=4.2
Requires-Dist: django-appconf
Provides-Extra: tests
Requires-Dist: pytest; extra == "tests"
Requires-Dist: pytest-cov; extra == "tests"
Requires-Dist: pytest-django; extra == "tests"
Requires-Dist: pytest-playwright; extra == "tests"
Requires-Dist: hypothesis; extra == "tests"
Requires-Dist: tox; extra == "tests"
Requires-Dist: ruff; extra == "tests"
Provides-Extra: docs
Requires-Dist: sphinx; extra == "docs"
Requires-Dist: sphinx-rtd-theme; extra == "docs"
Provides-Extra: release
Requires-Dist: tbump; extra == "release"
Dynamic: license-file
